{
  "name": "PARFUMER ATELIER",
  "emoji": "🏬",
  "website": "https://parfumeratelier.ru/",
  "chat": "https://parfumeratelier.ru/",
  "description": "Сеть распивочных по всей стране с очень стильным интерьером и услужливыми консультантами.",
  "authenticity": "⚠️ Есть сомнения в подлинности",
  "price": "💲💲 Средние цены",
  "fragrances": "🌟 Много популярных ароматов в распив",
  "reviews": "⭐ 3.8 (220 отзывов)",
  "rating": 3.8,
  "pros": [
    "🏬 Сеть распивочных представлена в разных городах.",
    "🎨 Очень стильный интерьер, приятная атмосфера.",
    "👥 Вежливые и услужливые консультанты.",
    "💎 В наличии много популярных ароматов в распив.",
    "💰 Средние цены, не завышены."
  ],
  "cons": [
    "🔍 Помимо брендовых ароматов есть одинаковые графины с неизвестной субстанцией.",
    "❓ Менеджеры утверждают, что это оригинал с завода, но есть сомнения.",
    "⚠️ Несколько раз были замечены подделки на полках с брендовыми ароматами."
  ],
  "customer_reviews": [
    {
      "author": "Анастасия В.",
      "text": "Очень красивый интерьер, но некоторые ароматы вызывают вопросы. 🤔"
    },
    {
      "author": "Олег Н.",
      "text": "Распив удобный, консультанты приятные, но вот эти одинаковые графины меня смущают... 😕"
    },
    {
      "author": "Мария К.",
      "text": "Популярные ароматы есть, но пару раз видела откровенные подделки. 😡"
    },
    {
      "author": "Игорь Л.",
      "text": "Цены нормальные, но хотелось бы больше уверенности в подлинности парфюма. 🧐"
    }
  ]
}